llama_index/py.typed
llama_index/vector_stores/docarray/__init__.py
llama_index/vector_stores/docarray/base.py
llama_index/vector_stores/docarray/hnsw.py
llama_index/vector_stores/docarray/in_memory.py
llama_index_vector_stores_docarray-0.4.1.dist-info/METADATA
llama_index_vector_stores_docarray-0.4.1.dist-info/WHEEL
llama_index_vector_stores_docarray-0.4.1.dist-info/licenses/LICENSE
llama_index_vector_stores_docarray-0.4.1.dist-info/RECORD
