Metadata-Version: 2.4
Name: llama-index-vector-stores-docarray
Version: 0.4.1
Summary: llama-index vector stores docarray integration
Author-email: Your Name <you@example.com>
License-Expression: MIT
License-File: LICENSE
Requires-Python: <4.0,>=3.9
Requires-Dist: docarray<0.41,>=0.40.0
Requires-Dist: llama-index-core<0.15,>=0.13.0
